python_template_test_pkg/__init__.py
python_template_test_pkg-1.3.0.dist-info/LICENSE
python_template_test_pkg-1.3.0.dist-info/METADATA
python_template_test_pkg-1.3.0.dist-info/WHEEL
python_template_test_pkg-1.3.0.dist-info/top_level.txt
python_template_test_pkg-1.3.0.dist-info/RECORD
